{
  "slug": "birthday-party-ideas",
  "title": "2024年最受歡迎的生日派對主題推薦",
  "excerpt": "探索今年最熱門的生日派對主題靈感，從經典到創新，為您的生日派對找到完美的佈置方案。",
  "content": [
    {
      "type": "paragraph",
      "text": "生日派對是慶祝生命中特別時刻的重要活動。選擇一個合適的主題不僅能讓派對更有趣，還能為壽星和賓客留下深刻印象。"
    },
    {
      "type": "heading",
      "level": 2,
      "text": "熱門派對主題推薦"
    },
    {
      "type": "heading",
      "level": 3,
      "text": "1. 夢幻獨角獸主題"
    },
    {
      "type": "paragraph",
      "text": "粉色、紫色和金色的配色，配上獨角獸造型氣球和裝飾，打造童話般的派對氛圍，特別受小朋友喜愛。"
    },
    {
      "type": "heading",
      "level": 3,
      "text": "2. 簡約優雅主題"
    },
    {
      "type": "paragraph",
      "text": "使用中性色調如白色、米色和金色，搭配簡約的氣球拱門，適合成人生日派對，展現品味與格調。"
    },
    {
      "type": "heading",
      "level": 3,
      "text": "3. 超級英雄主題"
    },
    {
      "type": "paragraph",
      "text": "以孩子最愛的超級英雄為主題，使用鮮豔的原色系氣球，創造充滿動感的派對空間。"
    },
    {
      "type": "divider"
    },
    {
      "type": "heading",
      "level": 2,
      "text": "佈置要點"
    },
    {
      "type": "list",
      "ordered": false,
      "items": [
        "提前2-3週開始規劃，確保有充足時間準備",
        "選擇與主題相符的顏色和裝飾元素",
        "考慮場地大小，合理安排佈置位置",
        "準備拍照區，讓賓客留下美好回憶",
        "注意安全，確保氣球和裝飾物穩固安裝"
      ]
    },
    {
      "type": "image",
      "src": "https://images.unsplash.com/photo-1464366400600-7168b8af9bc3?w=800&q=80",
      "alt": "生日派對氣球佈置",
      "caption": "精心設計的主題佈置讓生日派對更難忘"
    },
    {
      "type": "paragraph",
      "text": "想要打造完美的生日派對？BoboParty 提供多種主題佈置方案和專業建議，讓您的派對獨一無二。立即聯絡我們，開始規劃您的夢想派對吧！"
    }
  ],
  "author": "BoboParty 編輯團隊",
  "publishedAt": "2024-03-10",
  "featuredImage": "https://images.unsplash.com/photo-1464366400600-7168b8af9bc3?w=800&q=80",
  "tags": ["生日派對", "派對主題", "兒童派對", "派對策劃"],
  "seo": {
    "metaTitle": "2024年最受歡迎的生日派對主題 | BoboParty",
    "metaDescription": "探索最新生日派對主題靈感，包括獨角獸、簡約優雅、超級英雄等熱門主題，讓您的派對與眾不同。",
    "keywords": ["生日派對主題", "派對佈置靈感", "兒童生日派對", "派對裝飾", "香港派對策劃"]
  }
}
